{
    "SMBHD__FormConfig__c": [
        {
            "attributes": {
                "type": "SMBHD__FormConfig__c",
                "url": "/services/data/v34.0/sobjects/SMBHD__FormConfig__c/a00i000000LxoBXAAZ"
            },
            "OwnerId": "005i0000003KWWxAAO",
            "Name": "Management Agreement",
            "SMBHD__ObjectType__c": "SMBHD__LMS_Form__c",
            "Id": "a00i000000LxoBXAAZ",
            "SMBHD__PageConfig__c": [
                {
                    "attributes": {
                        "type": "SMBHD__PageConfig__c",
                        "url": "/services/data/v34.0/sobjects/SMBHD__PageConfig__c/a01i000000GEAW6AAP"
                    },
                    "Name": "Form Owner Information",
                    "SMBHD__FormConfig__c": "a00i000000LxoBXAAZ",
                    "SMBHD__Index__c": 0,
                    "Id": "a01i000000GEAW6AAP",
                    "SMBHD__PageElementConfig__c": [
                        {
                            "attributes": {
                                "type": "SMBHD__PageElementConfig__c",
                                "url": "/services/data/v34.0/sobjects/SMBHD__PageElementConfig__c/a03i000000CcTNrAAN"
                            },
                            "Name": "Instructions",
                            "SMBHD__Type__c": "Html",
                            "SMBHD__Index__c": 0,
                            "SMBHD__PageConfig__c": "a01i000000GEAW6AAP",
                            "SMBHD__Text_Area__c": "<div class=\"alert alert-info\">The Form Owner is the person that initially fills out and saves this form. This information will be automatically generated by the system.       \r\n</div>",
                            "SMBHD__Required__c": false,
                            "SMBHD__Read_Only__c": false,
                            "Id": "a03i000000CcTNrAAN"
                        }
                    ]
                },
                {
                    "attributes": {
                        "type": "SMBHD__PageConfig__c",
                        "url": "/services/data/v34.0/sobjects/SMBHD__PageConfig__c/a01i000000GEAiTAAX"
                    },
                    "Name": "General Information",
                    "SMBHD__FormConfig__c": "a00i000000LxoBXAAZ",
                    "SMBHD__Index__c": 1,
                    "Id": "a01i000000GEAiTAAX",
                    "SMBHD__PageElementConfig__c": [
                        {
                            "attributes": {
                                "type": "SMBHD__PageElementConfig__c",
                                "url": "/services/data/v34.0/sobjects/SMBHD__PageElementConfig__c/a03i000000CcTOpAAN"
                            },
                            "Name": "Page Instructions",
                            "SMBHD__Type__c": "Html",
                            "SMBHD__Index__c": 1,
                            "SMBHD__PageConfig__c": "a01i000000GEAiTAAX",
                            "SMBHD__Text_Area__c": "<div class=\"alert alert-info\">Market Type and Market Sub-Type are automatically generated by the system based on the Opportunity entered in the ACCOUNT (PROPERTY) INFORMATION section.\t\r\n</div>\r\n<div class=\"alert alert-info\">Duties of consultant should be attached.</div>\r\n<div class=\"alert alert-danger\">NOTE: A One-Time Special Event is an operation in which we provide labor and materials relating to parking management, valet services or other services that are not an ongoing operation beyond the Event itself. For example, a client may request valet services for private function such as a wedding, two-week county fair, or holiday shuttle service. This does not apply to consulting agreements that are covered in a separate Company policy.  Each One-Time Special Event must be treated as a new location. Therefore, it must be set up in the Company’s LMS, with its own unique location number assigned to it.\t\r\n</div>",
                            "SMBHD__Required__c": false,
                            "SMBHD__Read_Only__c": false,
                            "Id": "a03i000000CcTOpAAN"
                        },
                        {
                            "attributes": {
                                "type": "SMBHD__PageElementConfig__c",
                                "url": "/services/data/v34.0/sobjects/SMBHD__PageElementConfig__c/a03i000000CcTQFAA3"
                            },
                            "Name": "Location Name",
                            "SMBHD__Type__c": "Question",
                            "SMBHD__FieldName__c": "SMBHD__Product_Name__c",
                            "SMBHD__Index__c": 2,
                            "SMBHD__PageConfig__c": "a01i000000GEAiTAAX",
                            "SMBHD__Required__c": true,
                            "SMBHD__Read_Only__c": false,
                            "Id": "a03i000000CcTQFAA3"
                        },
                        {
                            "attributes": {
                                "type": "SMBHD__PageElementConfig__c",
                                "url": "/services/data/v34.0/sobjects/SMBHD__PageElementConfig__c/a03i000000CcTYjAAN"
                            },
                            "Name": "What do you need from the Legal Department?",
                            "SMBHD__Type__c": "Question",
                            "SMBHD__FieldName__c": "SMBHD__Legal_Department_Need__c",
                            "SMBHD__Index__c": 3,
                            "SMBHD__PageConfig__c": "a01i000000GEAiTAAX",
                            "SMBHD__Required__c": false,
                            "SMBHD__Read_Only__c": false,
                            "Id": "a03i000000CcTYjAAN"
                        },
                        {
                            "attributes": {
                                "type": "SMBHD__PageElementConfig__c",
                                "url": "/services/data/v34.0/sobjects/SMBHD__PageElementConfig__c/a03i000000CcTZDAA3"
                            },
                            "Name": "Are New Location Numbers Needed?",
                            "SMBHD__Type__c": "Question",
                            "SMBHD__FieldName__c": "SMBHD__New_Location_Numbers__c",
                            "SMBHD__Index__c": 4,
                            "SMBHD__PageConfig__c": "a01i000000GEAiTAAX",
                            "SMBHD__Required__c": false,
                            "SMBHD__Read_Only__c": false,
                            "Id": "a03i000000CcTZDAA3"
                        },
                        {
                            "attributes": {
                                "type": "SMBHD__PageElementConfig__c",
                                "url": "/services/data/v34.0/sobjects/SMBHD__PageElementConfig__c/a03i000000CcUEnAAN"
                            },
                            "Name": "What is the existing parent Location Number?",
                            "SMBHD__Type__c": "Question",
                            "SMBHD__FieldName__c": "SMBHD__Existing_Parent_Location_Number__c",
                            "SMBHD__Index__c": 5,
                            "SMBHD__PageConfig__c": "a01i000000GEAiTAAX",
                            "SMBHD__Required__c": false,
                            "SMBHD__Criteria_Pattern_String__c": "1 OR 2",
                            "SMBHD__Read_Only__c": false,
                            "Id": "a03i000000CcUEnAAN"
                        },
                        {
                            "attributes": {
                                "type": "SMBHD__PageElementConfig__c",
                                "url": "/services/data/v34.0/sobjects/SMBHD__PageElementConfig__c/a03i000000Ce6F8AAJ"
                            },
                            "Name": "Test Field",
                            "SMBHD__Type__c": "Question",
                            "SMBHD__FieldName__c": "SMBHD__Existing_Parent_Location_Number__c",
                            "SMBHD__Index__c": 6,
                            "SMBHD__PageConfig__c": "a01i000000GEAiTAAX",
                            "SMBHD__Required__c": false,
                            "SMBHD__Criteria_Pattern_String__c": "1 or 2 or 3",
                            "SMBHD__Read_Only__c": false,
                            "Id": "a03i000000Ce6F8AAJ",
                            "SMBHD__QueryCriterion__c": [
                                {
                                    "attributes": {
                                        "type": "SMBHD__QueryCriterion__c",
                                        "url": "/services/data/v34.0/sobjects/SMBHD__QueryCriterion__c/a05i000000Eb5bYAAR"
                                    },
                                    "Name": "a05i000000Eb5bY",
                                    "SMBHD__FieldName__c": "SMBHD__New_Location_Numbers__c",
                                    "SMBHD__Operator__c": "Equals",
                                    "SMBHD__Value__c": "Yes",
                                    "SMBHD__PageElementConfig__c": "a03i000000Ce6F8AAJ",
                                    "Id": "a05i000000Eb5bYAAR"
                                },
                                {
                                    "attributes": {
                                        "type": "SMBHD__QueryCriterion__c",
                                        "url": "/services/data/v34.0/sobjects/SMBHD__QueryCriterion__c/a05i000000Eb9IXAAZ"
                                    },
                                    "Name": "a05i000000Eb9IX",
                                    "SMBHD__FieldName__c": "SMBHD__Account_Name__c",
                                    "SMBHD__Operator__c": "Equals",
                                    "SMBHD__Value__c": "001i000000qeHZoAAM",
                                    "SMBHD__PageElementConfig__c": "a03i000000Ce6F8AAJ",
                                    "Id": "a05i000000Eb9IXAAZ"
                                },
                                {
                                    "attributes": {
                                        "type": "SMBHD__QueryCriterion__c",
                                        "url": "/services/data/v34.0/sobjects/SMBHD__QueryCriterion__c/a05i000000Eb9IYAAZ"
                                    },
                                    "Name": "a05i000000Eb9IY",
                                    "SMBHD__FieldName__c": "SMBHD__Account_Type__c",
                                    "SMBHD__Operator__c": "Equals",
                                    "SMBHD__Value__c": "Target Account",
                                    "SMBHD__PageElementConfig__c": "a03i000000Ce6F8AAJ",
                                    "Id": "a05i000000Eb9IYAAZ"
                                }
                            ]
                        }
                    ]
                },
                {
                    "attributes": {
                        "type": "SMBHD__PageConfig__c",
                        "url": "/services/data/v34.0/sobjects/SMBHD__PageConfig__c/a01i000000GEBUeAAP"
                    },
                    "Name": "Account (Property) Information",
                    "SMBHD__FormConfig__c": "a00i000000LxoBXAAZ",
                    "SMBHD__Index__c": 2,
                    "Id": "a01i000000GEBUeAAP",
                    "SMBHD__PageElementConfig__c": [
                        {
                            "attributes": {
                                "type": "SMBHD__PageElementConfig__c",
                                "url": "/services/data/v34.0/sobjects/SMBHD__PageElementConfig__c/a03i000000CcThDAAV"
                            },
                            "Name": "Account Information",
                            "SMBHD__Type__c": "Html",
                            "SMBHD__Index__c": 0,
                            "SMBHD__PageConfig__c": "a01i000000GEBUeAAP",
                            "SMBHD__Text_Area__c": "<div class=\"alert alert-info\">Account information is automatically gernerated by the system based on the Opportunity entered in this section.</div>",
                            "SMBHD__Required__c": false,
                            "SMBHD__Read_Only__c": false,
                            "Id": "a03i000000CcThDAAV"
                        },
                        {
                            "attributes": {
                                "type": "SMBHD__PageElementConfig__c",
                                "url": "/services/data/v34.0/sobjects/SMBHD__PageElementConfig__c/a03i000000CcThSAAV"
                            },
                            "Name": "Is this location converting from a lease to a management agreement?",
                            "SMBHD__Type__c": "Question",
                            "SMBHD__FieldName__c": "Location_Converting_from_Lease__c",
                            "SMBHD__Index__c": 1,
                            "SMBHD__PageConfig__c": "a01i000000GEBUeAAP",
                            "SMBHD__Required__c": false,
                            "SMBHD__Read_Only__c": false,
                            "Id": "a03i000000CcThSAAV"
                        },
                        {
                            "attributes": {
                                "type": "SMBHD__PageElementConfig__c",
                                "url": "/services/data/v34.0/sobjects/SMBHD__PageElementConfig__c/a03i000000CcqPKAAZ"
                            },
                            "Name": "What is the Least Location Number",
                            "SMBHD__Type__c": "Question",
                            "SMBHD__FieldName__c": "Lease_Location_Number__c",
                            "SMBHD__Index__c": 2,
                            "SMBHD__PageConfig__c": "a01i000000GEBUeAAP",
                            "SMBHD__Required__c": false,
                            "SMBHD__Read_Only__c": false,
                            "Id": "a03i000000CcqPKAAZ"
                        },
                        {
                            "attributes": {
                                "type": "SMBHD__PageElementConfig__c",
                                "url": "/services/data/v34.0/sobjects/SMBHD__PageElementConfig__c/a03i000000CcqPPAAZ"
                            },
                            "Name": "Is this a change of clients?",
                            "SMBHD__Type__c": "Question",
                            "SMBHD__FieldName__c": "Change_of_Ownership__c",
                            "SMBHD__Index__c": 3,
                            "SMBHD__PageConfig__c": "a01i000000GEBUeAAP",
                            "SMBHD__Required__c": false,
                            "SMBHD__Read_Only__c": false,
                            "Id": "a03i000000CcqPPAAZ"
                        }
                    ]
                },
                {
                    "attributes": {
                        "type": "SMBHD__PageConfig__c",
                        "url": "/services/data/v34.0/sobjects/SMBHD__PageConfig__c/a01i000000GnjM9AAJ"
                    },
                    "Name": "Client (Contracting Party) Information",
                    "SMBHD__FormConfig__c": "a00i000000LxoBXAAZ",
                    "SMBHD__Index__c": 3,
                    "Id": "a01i000000GnjM9AAJ",
                    "SMBHD__PageElementConfig__c": [
                        {
                            "attributes": {
                                "type": "SMBHD__PageElementConfig__c",
                                "url": "/services/data/v34.0/sobjects/SMBHD__PageElementConfig__c/a03i000000CcqPoAAJ"
                            },
                            "Name": "Client Information",
                            "SMBHD__Type__c": "Html",
                            "SMBHD__Index__c": 0,
                            "SMBHD__PageConfig__c": "a01i000000GnjM9AAJ",
                            "SMBHD__Text_Area__c": "<div class=\"alert alert-info\">Client information is automatically generated by the system based on the Contact Person for Notices entered in this section.</div>",
                            "SMBHD__Required__c": false,
                            "SMBHD__Read_Only__c": false,
                            "Id": "a03i000000CcqPoAAJ"
                        }
                    ]
                }
            ]
        }
    ]
}